skybellpy/__init__.py
skybellpy/__main__.py
skybellpy/device.py
skybellpy/exceptions.py
skybellpy/utils.py
skybellpy/helpers/__init__.py
skybellpy/helpers/constants.py
skybellpy/helpers/errors.py
skybellpy-0.6.3.dist-info/LICENSE
skybellpy-0.6.3.dist-info/METADATA
skybellpy-0.6.3.dist-info/WHEEL
skybellpy-0.6.3.dist-info/entry_points.txt
skybellpy-0.6.3.dist-info/top_level.txt
skybellpy-0.6.3.dist-info/RECORD
