Metadata-Version: 2.1
Name: skybellpy
Version: 0.6.3
Summary: An Skybell HD Python library running on Python 3.
Home-page: https://github.com/MisterWil/skybellpy
Author: Wil Schrader
Author-email: wilrader@gmail.com
License: MIT
Platform: any
Classifier: Intended Audience :: Developers
Classifier: License :: OSI Approved :: MIT License
Classifier: Operating System :: OS Independent
Classifier: Programming Language :: Python :: 3.5
Classifier: Topic :: Home Automation
Requires-Dist: requests (<3,>=2)
Requires-Dist: colorlog (>=3.0.1)
